pyescher/__init__.py
pyescher/linplot.py
pyescher/transformations.py
pyescher-0.2.2.dist-info/METADATA
pyescher-0.2.2.dist-info/WHEEL
pyescher-0.2.2.dist-info/licenses/LICENSE
pyescher-0.2.2.dist-info/RECORD
