Metadata-Version: 2.4
Name: pyescher
Version: 0.2.2
Summary: A Matplotlib wrapper with more convenience and pretty plots with a style common in physics papers.
Project-URL: Homepage, https://github.com/FennisRobert/pyescher
Project-URL: Issues, https://github.com/FennisRobert/pyescher/issues
Author-email: Robert Fennis <fennisrobert@gmail.com>
License: MIT
License-File: LICENSE
Classifier: License :: OSI Approved :: MIT License
Classifier: Operating System :: OS Independent
Classifier: Programming Language :: Python :: 3
Requires-Python: >=3.10
Requires-Dist: loguru>=0.7.3
Requires-Dist: matplotlib<=3.9
Requires-Dist: numpy>=2.2
Requires-Dist: pip-tools>=7.4.1
Requires-Dist: twine>=6.1.0
